sopel_hackernews/__init__.py
sopel_hackernews-0.1.0.dist-info/COPYING
sopel_hackernews-0.1.0.dist-info/METADATA
sopel_hackernews-0.1.0.dist-info/WHEEL
sopel_hackernews-0.1.0.dist-info/entry_points.txt
sopel_hackernews-0.1.0.dist-info/top_level.txt
sopel_hackernews-0.1.0.dist-info/RECORD
