Metadata-Version: 2.1
Name: sopel-hackernews
Version: 0.1.0
Summary: Hacker News plugin for Sopel.
Author-email: dgw <dgw@technobabbl.es>
License: EFL-2.0
Project-URL: Homepage, https://github.com/sopel-irc/sopel-hackernews
Project-URL: Bug Tracker, https://github.com/sopel-irc/sopel-hackernews/issues
Keywords: sopel,plugin,hackernews,bot,irc
Platform: Linux x86, x86-64
Classifier: Development Status :: 4 - Beta
Classifier: Intended Audience :: Developers
Classifier: Intended Audience :: System Administrators
Classifier: License :: Eiffel Forum License (EFL)
Classifier: License :: OSI Approved :: Eiffel Forum License
Classifier: Topic :: Communications :: Chat :: Internet Relay Chat
Requires-Python: !=3.0,!=3.1,!=3.2,<4,>=2.7
License-File: COPYING
Requires-Dist: sopel <9,>=7.1
Requires-Dist: requests
Requires-Dist: pytz
